pyfancy/__init__.py
pyfancy/demo.py
pyfancy/pyfancy.py
pyfancy-2.4.5.dist-info/DESCRIPTION.rst
pyfancy-2.4.5.dist-info/METADATA
pyfancy-2.4.5.dist-info/RECORD
pyfancy-2.4.5.dist-info/WHEEL
pyfancy-2.4.5.dist-info/metadata.json
pyfancy-2.4.5.dist-info/top_level.txt
