Metadata-Version: 2.0
Name: pyfancy
Version: 2.4.5
Summary: "Simple terminal formatting in Python"
Home-page: https://github.com/ilovecode1/Pyfancy-2
Author: pyfancy
Author-email: aquahydration@gmail.com
License: MIT
Keywords: pyfancy ansi color colour terminal
Platform: UNKNOWN
Classifier: Development Status :: 4 - Beta
Classifier: Intended Audience :: Developers
Classifier: Topic :: Software Development :: Build Tools
Classifier: License :: OSI Approved :: MIT License
Classifier: Programming Language :: Python :: 2
Classifier: Programming Language :: Python :: 2.7
Classifier: Programming Language :: Python :: 3
Classifier: Programming Language :: Python :: 3.3
Classifier: Programming Language :: Python :: 3.4
Classifier: Programming Language :: Python :: 3.5
Classifier: Programming Language :: Python :: 3.6
